[
  {
    "id": 1,
    "name": "Samsung TV",
    "image": "../../assets/productImg/samsungTV.png",
    "MRP": 29.99,
    "price": 19.99,
    "discount": 10,
    "rating": 4.5,
    "isCarted": false,
    "category": "Television",
    "company": "Samsung"
  },
  {
    "id": 2,
    "name": "LG Air Conditioner",
    "image": "../../assets/productImg/LGAC.png",
    "MRP": 39.99,
    "price": 29.99,
    "discount": 15,
    "rating": 4.0,
    "isCarted": false,
    "category": "Air Conditioner",
    "company": "LG"
  },
  {
    "id": 3,
    "name": "Whirlpool Refrigerator",
    "image": "../../assets/productImg/WhirlpoolRefrigerator.png",
    "MRP": 49.99,
    "price": 39.99,
    "discount": 12,
    "rating": 4.5,
    "isCarted": false,
    "category": "Refrigerator",
    "company": "Whirlpool"
  },
  {
    "id": 4,
    "name": "Haier Washing Machine",
    "image": "../../assets/productImg/HaierWashingMachine.png",
    "MRP": 59.99,
    "price": 49.99,
    "discount": 15,
    "rating": 4.0,
    "isCarted": false,
    "category": "Washing Machine",
    "company": "Haier"
  },
  {
    "id": 5,
    "name": "Sony Home Theator",
    "image": "../../assets/productImg/SonyHomeTheator.png",
    "MRP": 69.99,
    "price": 59.99,
    "discount": 15,
    "rating": 4.5,
    "isCarted": false,
    "category": "Home Theater",
    "company": "Sony"
  },
  {
    "id": 6,
    "name": "Philips Mixer & Juicer",
    "image": "../../assets/productImg/PhilipsMixerJuicer.png",
    "MRP": 79.99,
    "price": 69.99,
    "discount": 15,
    "rating": 4.0,
    "isCarted": false,
    "category": "Mixer & Juicer",
    "company": "Philips"
  },
  {
    "id": 7,
    "name": "Panasonic Television",
    "image": "../../assets/productImg/PanasonicTV.png",
    "MRP": 89.99,
    "price": 79.99,
    "discount": 20,
    "rating": 4.5,
    "isCarted": false,
    "category": "Television",
    "company": "Panasonic"
  },
  {
    "id": 8,
    "name": "Panasonic Air Conditioner",
    "image": "../../assets/productImg/PanasonicAc.png",
    "MRP": 29.99,
    "price": 19.99,
    "discount": 12,
    "rating": 4.5,
    "isCarted": false,
    "category": "Air Conditioner",
    "company": "Panasonic"
  },
  {
    "id": 9,
    "name": "LG Television",
    "image": "../../assets/productImg/LGTV.png",
    "MRP": 19.99,
    "price": 9.99,
    "discount": 10,
    "rating": 4.5,
    "isCarted": false,
    "category": "Television",
    "company": "LG"
  },
  {
    "id": 10,
    "name": "Bajaj Mixer & Juicer",
    "image": "../../assets/productImg/bajajmixer.png",
    "MRP": 89.99,
    "price": 79.99,
    "discount": 12,
    "rating": 4.5,
    "isCarted": false,
    "category": "Mixer & Juicer",
    "company": "Bajaj"
  },
  {
    "id": 11,
    "name": "Samsung TV",
    "image": "../../assets/productImg/samsungTV.png",
    "MRP": 29.99,
    "price": 19.99,
    "discount": 15,
    "rating": 4.5,
    "isCarted": false,
    "category": "Television",
    "company": "Samsung"
  },
  {
    "id": 12,
    "name": "LG Air Conditioner",
    "image": "../../assets/productImg/LGAC.png",
    "MRP": 39.99,
    "price": 19.99,
    "discount": 30,
    "rating": 4.0,
    "isCarted": false,
    "category": "Air Conditioner",
    "company": "LG"
  },
  {
    "id": 13,
    "name": "Whirlpool Refrigerator",
    "image": "../../assets/productImg/WhirlpoolRefrigerator.png",
    "MRP": 49.99,
    "price": 29.99,
    "discount": 15,
    "rating": 4.5,
    "isCarted": false,
    "category": "Refrigerator",
    "company": "Whirlpool"
  },
  {
    "id": 14,
    "name": "Haier Washing Machine",
    "image": "../../assets/productImg/HaierWashingMachine.png",
    "MRP": 59.99,
    "price": 39.99,
    "discount": 13,
    "rating": 4.0,
    "isCarted": false,
    "category": "Washing Machine",
    "company": "Haier"
  },
  {
    "id": 15,
    "name": "Sony Home Theator",
    "image": "../../assets/productImg/SonyHomeTheator.png",
    "MRP": 69.99,
    "price": 59.99,
    "discount": 20,
    "rating": 4.5,
    "isCarted": false,
    "category": "Home Theater",
    "company": "Sony"
  },
  {
    "id": 16,
    "name": "Philips Mixer & Juicer",
    "image": "../../assets/productImg/PhilipsMixerJuicer.png",
    "MRP": 79.99,
    "price": 69.99,
    "discount": 12,
    "rating": 4.0,
    "isCarted": false,
    "category": "Mixer & Juicer",
    "company": "Philips"
  },
  {
    "id": 17,
    "name": "Panasonic Television",
    "image": "../../assets/productImg/PanasonicTV.png",
    "MRP": 89.99,
    "price": 79.99,
    "discount": 20,
    "rating": 4.5,
    "isCarted": false,
    "category": "Television",
    "company": "Panasonic"
  },
  {
    "id": 18,
    "name": "Panasonic Air Conditioner",
    "image": "../../assets/productImg/PanasonicAc.png",
    "MRP": 29.99,
    "price": 19.99,
    "discount": 12,
    "rating": 4.5,
    "isCarted": false,
    "category": "Air Conditioner",
    "company": "Panasonic"
  },
  {
    "id": 19,
    "name": "LG Television",
    "image": "../../assets/productImg/LGTV.png",
    "MRP": 19.99,
    "price": 9,
    "discount": 10,
    "rating": 4.5,
    "isCarted": false,
    "category": "Television",
    "company": "LG"
  },
  {
    "id": 20,
    "name": "Bajaj Mixer & Juicer",
    "image": "../../assets/productImg/bajajmixer.png",
    "MRP": 89.99,
    "price": 69.99,
    "discount": 30,
    "rating": 4.5,
    "isCarted": false,
    "category": "Mixer & Juicer",
    "company": "Bajaj"
  }
]